opening_hours/__init__.py
opening_hours/parse_opening_hours.py
opening_hours/patterns.py
opening_hours/models/__init__.py
opening_hours/models/day.py
opening_hours/models/days.py
opening_hours/models/time.py
opening_hours/models/times.py
jsonify_opening_hours-0.4.0.dist-info/LICENSE
jsonify_opening_hours-0.4.0.dist-info/METADATA
jsonify_opening_hours-0.4.0.dist-info/WHEEL
jsonify_opening_hours-0.4.0.dist-info/top_level.txt
jsonify_opening_hours-0.4.0.dist-info/RECORD
